historian_query.py
historian_query-0.0.1.dist-info/LICENSE
historian_query-0.0.1.dist-info/METADATA
historian_query-0.0.1.dist-info/WHEEL
historian_query-0.0.1.dist-info/top_level.txt
historian_query-0.0.1.dist-info/RECORD
