Metadata-Version: 2.1
Name: historian-query
Version: 0.0.1
Summary: Query regularized time series from raw historian data on Spark
Author-email: Edgars Jakobsons <ejakobsons@microsoft.com>, Harrington McDowelle <mcdowellehar@microsoft.com>
Project-URL: Homepage, https://github.com/microsoft/historian-query
Classifier: Programming Language :: Python :: 3
Classifier: License :: OSI Approved :: MIT License
Classifier: Operating System :: OS Independent
Requires-Python: >=3.7
License-File: LICENSE
Requires-Dist: pyspark >=3.4.1
Requires-Dist: dbl-tempo >=0.1.25
